rag_pipeline/__init__.py
rag_pipeline/pipeline.py
rag_pipeline/chunking/__init__.py
rag_pipeline/chunking/base.py
rag_pipeline/chunking/fixed_size.py
rag_pipeline/chunking/semantic.py
rag_pipeline/document_loaders/__init__.py
rag_pipeline/document_loaders/csv_loader.py
rag_pipeline/document_loaders/excel_loader.py
rag_pipeline/document_loaders/file_loader.py
rag_pipeline/document_loaders/jsonl_loader.py
rag_pipeline/document_loaders/pdf_loader.py
rag_pipeline/document_loaders/word_loader.py
rag_pipeline/embeddings/__init__.py
rag_pipeline/embeddings/base.py
rag_pipeline/embeddings/huggingface.py
rag_pipeline/embeddings/llamacpp.py
rag_pipeline/embeddings/ollama.py
rag_pipeline/embeddings/openai.py
rag_pipeline/llms/__init__.py
rag_pipeline/llms/base.py
rag_pipeline/llms/huggingface.py
rag_pipeline/llms/llamacpp.py
rag_pipeline/llms/ollama.py
rag_pipeline/llms/openai.py
rag_pipeline/retrievers/bm25.py
rag_pipeline/vector_stores/__init__.py
rag_pipeline/vector_stores/base.py
rag_pipeline/vector_stores/chromadb.py
rag_pipeline/vector_stores/faiss.py
rag_pipeline/vector_stores/pgvector.py
rag_pipeline/vector_stores/qdrant.py
rag_pipeline/vector_stores/weaviate.py
rag_pipeline_lib-0.1.1.dist-info/licenses/LICENSE
rag_pipeline_lib-0.1.1.dist-info/METADATA
rag_pipeline_lib-0.1.1.dist-info/WHEEL
rag_pipeline_lib-0.1.1.dist-info/top_level.txt
rag_pipeline_lib-0.1.1.dist-info/RECORD
