Metadata-Version: 2.4
Name: rag-pipeline-lib
Version: 0.1.1
Summary: Modüler, hibrit (dense + BM25) RAG pipeline kütüphanesi
Author-email: Adınız Soyadınız <mail@ornek.com>
License-Expression: MIT
Keywords: rag,retrieval,llm,nlp,vector,bm25,hybrid
Classifier: Programming Language :: Python :: 3
Classifier: Operating System :: OS Independent
Requires-Python: >=3.9
License-File: LICENSE
Requires-Dist: numpy>=1.22
Requires-Dist: requests>=2.31
Requires-Dist: rank-bm25>=0.2.2
Provides-Extra: pdf
Requires-Dist: pymupdf>=1.23; extra == "pdf"
Provides-Extra: excel
Requires-Dist: openpyxl>=3.1; extra == "excel"
Provides-Extra: word
Requires-Dist: python-docx>=1.0; extra == "word"
Provides-Extra: qdrant
Requires-Dist: qdrant-client>=1.7; extra == "qdrant"
Provides-Extra: chromadb
Requires-Dist: chromadb>=0.5; extra == "chromadb"
Provides-Extra: faiss
Requires-Dist: faiss-cpu>=1.7.4; extra == "faiss"
Provides-Extra: hf
Requires-Dist: sentence-transformers>=2.2.2; extra == "hf"
Provides-Extra: weaviate
Requires-Dist: weaviate-client>=4.6; extra == "weaviate"
Provides-Extra: openai
Requires-Dist: openai>=1.0; extra == "openai"
Provides-Extra: ollama
Dynamic: license-file
